jsonschema_pydantic_converter/__init__.py
jsonschema_pydantic_converter/_schema_utils.py
jsonschema_pydantic_converter/_type_converters.py
jsonschema_pydantic_converter/_validators.py
jsonschema_pydantic_converter/create_type_adapter.py
jsonschema_pydantic_converter/py.typed
jsonschema_pydantic_converter/transform.py
jsonschema_pydantic_converter-0.1.8.dist-info/METADATA
jsonschema_pydantic_converter-0.1.8.dist-info/WHEEL
jsonschema_pydantic_converter-0.1.8.dist-info/licenses/LICENSE
jsonschema_pydantic_converter-0.1.8.dist-info/RECORD
