Metadata-Version: 2.4
Name: jsonschema-pydantic-converter
Version: 0.1.8
Summary: Convert JSON Schema definitions to Pydantic models dynamically at runtime
Project-URL: Homepage, https://github.com/akshaylive/jsonschema-pydantic-converter
Project-URL: Repository, https://github.com/akshaylive/jsonschema-pydantic-converter
Maintainer-email: Akshaya Shanbhogue <akshay.live@gmail.com>
License: Apache-2.0
License-File: LICENSE
Keywords: conversion,json-schema,pydantic,schema,validation
Classifier: Development Status :: 3 - Alpha
Classifier: Intended Audience :: Developers
Classifier: License :: OSI Approved :: Apache Software License
Classifier: Programming Language :: Python :: 3
Classifier: Programming Language :: Python :: 3.10
Classifier: Programming Language :: Python :: 3.11
Classifier: Programming Language :: Python :: 3.12
Classifier: Programming Language :: Python :: 3.13
Classifier: Topic :: Software Development :: Libraries :: Python Modules
Requires-Python: >=3.10
Requires-Dist: pydantic>=2.0.0
